<?xml version="1.0" encoding="UTF-8"?>




<ui-command xmlns="http://www.efaps.org/xsd"
            xmlns:xsi="http://www.w3.org/2001/XMLSchema-instance"
            xsi:schemaLocation="http://www.efaps.org/xsd http://www.efaps.org/xsd/eFaps_1.0.xsd">
    <uuid>d9e4755b-ce8d-4d29-8646-78ca374fe0c6</uuid>
    <file-application>eFapsApp-TimeReport</file-application>
    
    <definition>
        <version-expression>(version==latest)</version-expression>
        <name>TimeReport_EmployeeReportTree_Position_Menu_Action_Create</name>
        

        <target>
            <form>TimeReport_EmployeeReportPositionForm</form>
            <execute program="org.efaps.esjp.timereport.EmployeeReport" method="createPosition"/>
        </target>
        

        <property name="Target">modal</property>
        <property name="TargetCmdRevise">true</property>
        <property name="TargetMode">create</property>
        <property name="TargetCreateType">TimeReport_EmployeeReportPosition</property>
        <property name="WindowHeight">460</property>
        <property name="WindowWidth">515</property>
    </definition>
</ui-command>
