<?xml version="1.0" encoding="UTF-8" standalone="no"?>

<ui-menu xmlns="http://www.efaps.org/xsd" xmlns:xsi="http://www.w3.org/2001/XMLSchema-instance"
    xsi:schemaLocation="http://www.efaps.org/xsd http://www.efaps.org/xsd/eFaps_1.0.xsd">
    <uuid>b9f71b47-95f3-414b-abaa-aaf976b4d8f5</uuid>
    <file-application>eFapsApp-TimeReport</file-application>
    
    <definition>
        <version-expression>(version==latest)</version-expression>
        <name>TimeReport_AttendanceTree_Menu</name>
        <childs>
            <child>TimeReport_AttendanceTree_Menu_Action</child>
        </childs>
    </definition>
</ui-menu>