<?xml version="1.0" encoding="UTF-8" standalone="no"?>

<datamodel-type xmlns="http://www.efaps.org/xsd"
    xmlns:xsi="http://www.w3.org/2001/XMLSchema-instance"
    xsi:schemaLocation="http://www.efaps.org/xsd http://www.efaps.org/xsd/eFaps_1.0.xsd">
    <uuid>611c9c47-44f8-47b1-be6d-815998e81b05</uuid>
    <file-application>eFapsApp-TimeReport</file-application>
    
    <definition>
        <version-expression>(version==latest)</version-expression>
        <name>TimeReport_AttendanceStartAbstract</name>
        <parent>TimeReport_AttendanceAbstract</parent>
        <purpose abstract="true" />
    </definition>
</datamodel-type>